{
"type": "FeatureCollection",
"name": "Ruang Evakuasi PT",
"crs": { "type": "name", "properties": { "name": "urn:ogc:def:crs:OGC:1.3:CRS84" } },
"features": [
{ "type": "Feature", "properties": { "KET": "Rumah Panggung", "Sumber": "Survey Lapangan oleh DPUTR Kab. Pati, Tahun 2019" }, "geometry": { "type": "Point", "coordinates": [ 110.932139016754192, -6.89372416539995 ] } },
{ "type": "Feature", "properties": { "KET": "Rumah Panggung", "Sumber": "Survey Lapangan oleh DPUTR Kab. Pati, Tahun 2019" }, "geometry": { "type": "Point", "coordinates": [ 111.0548490912538, -6.774580665030654 ] } },
{ "type": "Feature", "properties": { "KET": "Rumah Panggung", "Sumber": "Survey Lapangan oleh DPUTR Kab. Pati, Tahun 2019" }, "geometry": { "type": "Point", "coordinates": [ 111.093050760369792, -6.74664067010233 ] } },
{ "type": "Feature", "properties": { "KET": "Rumah Panggung", "Sumber": "Survey Lapangan oleh DPUTR Kab. Pati, Tahun 2019" }, "geometry": { "type": "Point", "coordinates": [ 111.053251067324538, -6.771617748511711 ] } },
{ "type": "Feature", "properties": { "KET": "Rumah Panggung", "Sumber": "Survey Lapangan oleh DPUTR Kab. Pati, Tahun 2019" }, "geometry": { "type": "Point", "coordinates": [ 111.142563514933371, -6.733715544234513 ] } }
]
}
